siris/__init__.py
siris/allowed_values.py
siris/scraper.py
siris/utils.py
siris_scraper-0.4.0.dist-info/LICENSE
siris_scraper-0.4.0.dist-info/METADATA
siris_scraper-0.4.0.dist-info/WHEEL
siris_scraper-0.4.0.dist-info/top_level.txt
siris_scraper-0.4.0.dist-info/RECORD
