Metadata-Version: 2.1
Name: siris-scraper
Version: 0.4.0
Summary: A scraper of statistical data from the Siris database of Skolverket, built on top of Statscraper.
Home-page: https://github.com/jplusplus/siris_scraper
Author: Jens Finnäs
Author-email: jens.finnas@gmail.com
License: MIT
Download-URL: https://github.com/jplusplus/siris_scraper/archive/0.4.0.tar.gz
Platform: UNKNOWN
License-File: LICENSE
Requires-Dist: statscraper
Requires-Dist: requests
Requires-Dist: beautifulsoup4
Requires-Dist: lxml
